[
    {
        "id": 0,
        "title": "Flexible Tablet Stand"
    },
    {
        "id": 1,
        "title": "Canvas Picture"
    },
    {
        "id": 2,
        "title": "Whiskey Barrel"
    },
    {
        "id":3,
        "title": "Love, Laugh, Kill"
    },
    {
        "id": 4,
        "title": "Working Trebuchet"
    },
    {
        "id": 5,
        "title": "Tomato Planter"
    },
    {
        "id": 6,
        "title": "Jar of Rocks"
    },
    {
        "id": 7,
        "title": "Bathrobe"
    },
    {
        "id": 8,
        "title": "Beer of the Month Club"
    },
    {
        "id": 9,
        "title": "Cookbook"
    },
    {
        "id": 10,
        "title": "Tree Log"
    },
    {
        "id": 11,
        "title": "Book"
    },
    {
        "id": 12,
        "title": "Picture of Lake"
    },
    {
        "id": 13,
        "title": "Slice of Pizza"
    },
    {
        "id": 14,
        "title": "Heated Seat Cover"
    },
    {
        "id": 15,
        "title": "Photo Puzzle"
    },
    {
        "id": 16,
        "title": "VR Headset"
    },
    {
        "id": 17,
        "title": "Hair Ties"
    },
    {
        "id": 18,
        "title": "Rock from Moon"
    },
    {
        "id": 19,
        "title": "Zipline Adventure"
    },
    {
        "id": 20,
        "title": "Magnetic Toast"
    },
    {
        "id": 21,
        "title": "Beef Jerky of the Month Club"
    },
    {
        "id": 22,
        "title": "Picture of Picture"
    },
    {
        "id": 23,
        "title": "Empty Cool Whip Cereal Bowl"
    },
    {
        "id": 24,
        "title": "Key Chain"
    }
]